esengine/__init__.py
esengine/document.py
esengine/embedded_document.py
esengine/exceptions.py
esengine/fields.py
esengine/mapping.py
esengine/bases/__init__.py
esengine/bases/document.py
esengine/bases/field.py
esengine/bases/metaclass.py
esengine/bases/py3.py
esengine/bases/result.py
esengine/utils/__init__.py
esengine/utils/example.py
esengine/utils/pagination.py
esengine/utils/validation.py
esengine/utils/payload/__init__.py
esengine/utils/payload/aggregates.py
esengine/utils/payload/base.py
esengine/utils/payload/exception.py
esengine/utils/payload/filters.py
esengine/utils/payload/meta.py
esengine/utils/payload/meta_util.py
esengine/utils/payload/queries.py
esengine/utils/payload/suggesters.py
tests/__init__.py
tests/conftest.py
tests/test_base_document.py
tests/test_base_field.py
tests/test_document.py
tests/test_embedded_document.py
tests/test_fields.py
tests/test_mapping.py
tests/test_metaclass.py
tests/test_payload.py
tests/test_results.py
tests/test_utils.py
esengine-0.1.0.dist-info/LICENSE
esengine-0.1.0.dist-info/METADATA
esengine-0.1.0.dist-info/WHEEL
esengine-0.1.0.dist-info/top_level.txt
esengine-0.1.0.dist-info/RECORD
