Metadata-Version: 2.1
Name: esengine
Version: 0.1.0
Summary: Elasticsearch ODM inspired on MongoEngine
Home-page: https://github.com/seek-ai/esengine
Author: Catholabs
Author-email: catholabs@catho.com
License: MIT
Platform: any
Classifier: Development Status :: 4 - Beta
Classifier: Intended Audience :: Developers
Classifier: Operating System :: POSIX
Classifier: Operating System :: POSIX :: Linux
Classifier: License :: OSI Approved :: MIT License
Classifier: Programming Language :: Python :: 3
Classifier: Programming Language :: Python :: 3.5
Classifier: Programming Language :: Python :: 3.6
Requires-Dist: python-dateutil
Requires-Dist: six (==1.10.0)
Provides-Extra: es0
Requires-Dist: elasticsearch (<1.0.0) ; extra == 'es0'
Provides-Extra: es1
Requires-Dist: elasticsearch (<2.0.0,>=1.0.0) ; extra == 'es1'
Provides-Extra: es2
Requires-Dist: elasticsearch (<3.0.0,>=2.0.0) ; extra == 'es2'
